contentful/__init__.py
contentful/management.py
contentful/test_management.py
skyscanner_contentful_management-1.0.0.dist-info/DESCRIPTION.rst
skyscanner_contentful_management-1.0.0.dist-info/METADATA
skyscanner_contentful_management-1.0.0.dist-info/RECORD
skyscanner_contentful_management-1.0.0.dist-info/WHEEL
skyscanner_contentful_management-1.0.0.dist-info/entry_points.txt
skyscanner_contentful_management-1.0.0.dist-info/metadata.json
skyscanner_contentful_management-1.0.0.dist-info/top_level.txt
