Metadata-Version: 2.0
Name: skyscanner-contentful-management
Version: 1.0.0
Summary: UNKNOWN
Home-page: https://github.com/skyscanner/skyscanner-contentful-management
Author: Travel Content Platform
Author-email: TravelContentPlatformSquad@skyscanner.net
License: UNKNOWN
Platform: UNKNOWN
Requires-Dist: requests
Requires-Dist: click
